src/design/debounce.sv
module debounce (
    input  logic clk,
    input  logic rst,           // reset activo en bajo
    input  logic key,           // señal de entrada (fila del teclado, activa en bajo)
    output logic key_pressed    // salida debounced (0 = tecla estable en 0, 1 = caso contrario)
);

    // Parámetro para ajustar el tiempo de debounce.
    // El tiempo de estabilización ≈ 2^N ciclos de reloj.
    parameter int N = 12;

    logic [N-1:0] reg_sat, reg_next;
    logic SAMPLE1, SAMPLE2;
    logic reg_reset;
    logic reg_add;

    // Señal estable (debounced) de la tecla
    logic key_stable;

    // Detecta cambio en la señal sincronizada
    assign reg_reset = (SAMPLE1 ^ SAMPLE2);
    // Sigue contando mientras no se haya saturado el MSB
    assign reg_add   = ~reg_sat[N-1];

    // Lógica del contador de estabilidad
    always_comb begin
        case ({reg_reset, reg_add})
            2'b00: reg_next = reg_sat;          // sin cambio y ya saturado → mantener
            2'b01: reg_next = reg_sat + 1'b1;   // sin cambio y no saturado → contar
            default: reg_next = {N{1'b0}};      // hubo cambio → resetear contador
        endcase
    end

    always_ff @(posedge clk or negedge rst) begin
        if (!rst) begin
            SAMPLE1     <= 1'b1;
            SAMPLE2     <= 1'b1;
            reg_sat     <= '0;
            key_stable  <= 1'b1;  // sin tecla presionada al inicio
            key_pressed <= 1'b1;  // salida en 1 por defecto
        end else begin
            // Doble muestreo para sincronizar la señal al reloj
            SAMPLE1 <= key;
            SAMPLE2 <= SAMPLE1;

            // Actualizar contador
            reg_sat <= reg_next;

            // Cuando el contador se satura, aceptamos el nuevo valor estable
            if (reg_sat[N-1]) begin
                key_stable <= SAMPLE2;
            end

            // Salida activa en bajo:
            //  - 0 cuando la tecla se ha estabilizado en 0 (presionada)
            //  - 1 en cualquier otro caso
            key_pressed <= key_stable ? 1'b1 : 1'b0;
        end
    end
endmodule

src/sim/tb_debounce.sv
`timescale 1ns/1ps

module tb_debounce;

    // Parámetro para esta simulación
    localparam int N_TB = 16;
    localparam int STABLE_CYCLES = (1 << N_TB) + 2; // algo más que 2^N

    // Señales
    logic clk;
    logic rst;          // reset activo en bajo
    logic key;          // entrada (fila del teclado)
    logic key_pressed;  // salida del debounce

    // Instancia del DUT
    debounce #(
        .N(N_TB)
    ) dut (
        .clk        (clk),
        .rst        (rst),
        .key        (key),
        .key_pressed(key_pressed)
    );

    // Generador de reloj: periodo 10 ns
    initial clk = 0;
    always #5 clk = ~clk;

    // Tarea para esperar N flancos de reloj
    task automatic wait_cycles(input int n);
        int i;
        begin
            for (i = 0; i < n; i++) begin
                @(posedge clk);
            end
        end
    endtask

    // Tarea: generar rebotes rápidos alrededor de un valor objetivo
    task automatic bounce_key(
        input logic final_value,
        input int   num_bounces,
        input int   cycles_between_bounces
    );
        int i;
        begin
            for (i = 0; i < num_bounces; i++) begin
                key = ~final_value;
                wait_cycles(cycles_between_bounces);
                key = final_value;
                wait_cycles(cycles_between_bounces);
            end
        end
    endtask

    initial begin
        // Inicialización
        rst = 0;
        key = 1;  // sin tecla presionada (activa en bajo)

        // Volcado de señales
        $dumpfile("tb_debounce.vcd");
        $dumpvars(0, tb_debounce);

        // Mantener reset un rato
        wait_cycles(4);
        rst = 1;
        $display("[%0t] Reset liberado", $time);

        // ============================
        // TEST 1: reposo estable en 1
        // ============================
        wait_cycles(STABLE_CYCLES);

        if (key_pressed !== 1'b1) begin
            $error("[%0t] TEST 1 FALLÓ: key=1 estable, se esperaba key_pressed=1, se obtuvo %b",
                   $time, key_pressed);
        end else begin
            $display("[%0t] TEST 1 OK: reposo estable, key_pressed=%b", $time, key_pressed);
        end

        // ==================================
        // TEST 2: rebotes al presionar (1→0)
        // ==================================
        $display("[%0t] TEST 2: rebotes al presionar", $time);
        bounce_key(1'b0, /*num_bounces*/ 3, /*cycles_between_bounces*/ 1);

        // Tras rebotes, aún no hemos dejado estable mucho tiempo
        if (key_pressed !== 1'b1) begin
            $error("[%0t] TEST 2 FALLÓ: tras rebotes, se esperaba key_pressed=1, se obtuvo %b",
                   $time, key_pressed);
        end else begin
            $display("[%0t] TEST 2 OK: rebotes no cambian salida, key_pressed=%b",
                     $time, key_pressed);
        end

        // ======================================
        // TEST 3: pulsación estable (key = 0)
        // ======================================
        $display("[%0t] TEST 3: pulsación estable", $time);
        key = 0;  // tecla presionada (activa en bajo)

        wait_cycles(STABLE_CYCLES);

        if (key_pressed !== 1'b0) begin
            $error("[%0t] TEST 3 FALLÓ: key=0 estable, se esperaba key_pressed=0, se obtuvo %b",
                   $time, key_pressed);
        end else begin
            $display("[%0t] TEST 3 OK: tecla presionada estable, key_pressed=%b",
                     $time, key_pressed);
        end

        // =====================================
        // TEST 4: rebotes al soltar (0→1)
        // =====================================
        $display("[%0t] TEST 4: rebotes al soltar", $time);

        // Rebotes alrededor de 1 (soltar la tecla con ruido)
        bounce_key(1'b1, /*num_bounces*/ 3, /*cycles_between_bounces*/ 1);

        // Todavía puede estar debouncing, ahora dejamos key=1 estable
        key = 1;
        wait_cycles(STABLE_CYCLES);

        if (key_pressed !== 1'b1) begin
            $error("[%0t] TEST 4 FALLÓ: key=1 estable, se esperaba key_pressed=1, se obtuvo %b",
                   $time, key_pressed);
        end else begin
            $display("[%0t] TEST 4 OK: tecla soltada estable, key_pressed=%b",
                     $time, key_pressed);
        end

        $display("[%0t] Fin de la simulación", $time);
        $finish;
    end

endmodule

src/build/tb_debounce.vcd
$date
	Sun Nov 16 19:10:15 2025
$end
$version
	Icarus Verilog
$end
$timescale
	1ps
$end
$scope module tb_debounce $end
$var wire 1 ! key_pressed $end
$var parameter 32 " N_TB $end
$var parameter 32 # STABLE_CYCLES $end
$var reg 1 $ clk $end
$var reg 1 % key $end
$var reg 1 & rst $end
$scope module dut $end
$var wire 1 $ clk $end
$var wire 1 % key $end
$var wire 1 ' reg_add $end
$var wire 1 ( reg_reset $end
$var wire 1 & rst $end
$var parameter 32 ) N $end
$var reg 1 * SAMPLE1 $end
$var reg 1 + SAMPLE2 $end
$var reg 1 ! key_pressed $end
$var reg 1 , key_stable $end
$var reg 4 - reg_next [3:0] $end
$var reg 4 . reg_sat [3:0] $end
$upscope $end
$scope task bounce_key $end
$upscope $end
$scope task wait_cycles $end
$upscope $end
$upscope $end
$enddefinitions $end
$comment Show the parameter values. $end
$dumpall
b100 )
b10010 #
b100 "
$end
#0
$dumpvars
b0 .
b1 -
1,
1+
1*
0(
1'
0&
1%
0$
1!
$end
#5000
1$
#10000
0$
#15000
1$
#20000
0$
#25000
1$
#30000
0$
#35000
b10 -
b1 .
1&
1$
#40000
0$
#45000
b11 -
b10 .
1$
#50000
0$
#55000
b100 -
b11 .
1$
#60000
0$
#65000
b101 -
b100 .
1$
#70000
0$
#75000
b110 -
b101 .
1$
#80000
0$
#85000
b111 -
b110 .
1$
#90000
0$
#95000
b1000 -
b111 .
1$
#100000
0$
#105000
0'
b1000 -
b1000 .
1$
#110000
0$
#115000
1$
#120000
0$
#125000
1$
#130000
0$
#135000
1$
#140000
0$
#145000
1$
#150000
0$
#155000
1$
#160000
0$
#165000
1$
#170000
0$
#175000
1$
#180000
0$
#185000
1$
#190000
0$
#195000
1$
#200000
0$
#205000
1$
#210000
0$
#215000
1$
#220000
0$
#225000
b0 -
1(
0*
0%
1$
#230000
0$
#235000
1'
b0 .
0+
1*
1%
1$
#240000
0$
#245000
1+
0*
0%
1$
#250000
0$
#255000
0+
1*
1%
1$
#260000
0$
#265000
1+
0*
0%
1$
#270000
0$
#275000
b1 -
0(
0+
1$
#280000
0$
#285000
b10 -
b1 .
1$
#290000
0$
#295000
b11 -
b10 .
1$
#300000
0$
#305000
b100 -
b11 .
1$
#310000
0$
#315000
b101 -
b100 .
1$
#320000
0$
#325000
b110 -
b101 .
1$
#330000
0$
#335000
b111 -
b110 .
1$
#340000
0$
#345000
b1000 -
b111 .
1$
#350000
0$
#355000
0'
b1000 -
b1000 .
1$
#360000
0$
#365000
0,
1$
#370000
0$
#375000
0!
1$
#380000
0$
#385000
1$
#390000
0$
#395000
1$
#400000
0$
#405000
1$
#410000
0$
#415000
1$
#420000
0$
#425000
1$
#430000
0$
#435000
1$
#440000
0$
#445000
1$
#450000
0$
#455000
1$
#460000
0$
#465000
b0 -
1(
1*
1%
1$
#470000
0$
#475000
1'
b0 .
1+
0*
0%
1$
#480000
0$
#485000
0+
1*
1%
1$
#490000
0$
#495000
1+
0*
0%
1$
#500000
0$
#505000
0+
1*
1%
1$
#510000
0$
#515000
b1 -
0(
1+
1$
#520000
0$
#525000
b10 -
b1 .
1$
#530000
0$
#535000
b11 -
b10 .
1$
#540000
0$
#545000
b100 -
b11 .
1$
#550000
0$
#555000
b101 -
b100 .
1$
#560000
0$
#565000
b110 -
b101 .
1$
#570000
0$
#575000
b111 -
b110 .
1$
#580000
0$
#585000
b1000 -
b111 .
1$
#590000
0$
#595000
0'
b1000 -
b1000 .
1$
#600000
0$
#605000
1,
1$
#610000
0$
#615000
1!
1$
