src/design/operacion.sv
module operacion (
    input  logic       clk,
    input  logic       rst_n,    // reset global activo en bajo
    input  logic       start,    // pulso 1 ciclo para iniciar la división
    input  logic [7:0] a_bcd,    // Dividendo en BCD: {decenas, unidades}
    input  logic [7:0] b_bcd,    // Divisor   en BCD: {decenas, unidades}
    output logic [3:0] cociente, // Q[3:0]
    output logic [3:0] resto     // R[3:0]
);

    // --------------------------------------------------
    // 1) Conversión BCD -> binario
    // --------------------------------------------------
    logic [3:0] a_dec, a_uni;
    logic [3:0] b_dec, b_uni;
    logic [3:0] A_bin;   // dividendo
    logic [3:0] B_bin;   // divisor

    always_comb begin
        // si la decena es 1 => 10, si no => 0
        a_dec = (a_bcd[7:4] == 4'b0001) ? 4'b1010    : 4'b0000;
        a_uni = (a_bcd[3:0] != 4'b1111) ? a_bcd[3:0] : 4'b0000;
        b_dec = (b_bcd[7:4] == 4'b0001) ? 4'b1010    : 4'b0000;
        b_uni = (b_bcd[3:0] != 4'b1111) ? b_bcd[3:0] : 4'b0000;

        A_bin = a_uni + a_dec;
        B_bin = b_uni + b_dec;
    end

    // --------------------------------------------------
    // 2) Registros del algoritmo (resto, cociente, índice, running)
    // --------------------------------------------------
    logic [3:0] resto_reg;
    logic [3:0] coc_reg;
    logic [1:0] idx;
    logic       running;

    logic [3:0] R_shift;
    logic signed [4:0] D;

    always_comb begin
        R_shift = {resto_reg[2:0], A_bin[idx]};                  // R = {R'<<1, A_i}
        D       = $signed({1'b0, R_shift}) - $signed({1'b0, B_bin}); // D = R - B
    end

    // --------------------------------------------------
    // 3) Secuencial con start (sin latches)
    // --------------------------------------------------
    always_ff @(posedge clk or negedge rst_n) begin
        if (!rst_n) begin
            resto_reg <= 4'b0000;
            coc_reg   <= 4'b0000;
            idx       <= 2'd0;
            running   <= 1'b0;
        end else begin
            if (start) begin
                // iniciar nueva división
                resto_reg <= 4'b0000;
                coc_reg   <= 4'b0000;
                idx       <= 2'd3;
                running   <= 1'b1;
            end else if (running) begin
                if (D < 0) begin
                    coc_reg[idx] <= 1'b0;
                    resto_reg    <= R_shift;
                end else begin
                    coc_reg[idx] <= 1'b1;
                    resto_reg    <= D[3:0];
                end

                if (idx == 2'd0)
                    running <= 1'b0;     // terminamos
                else
                    idx <= idx - 2'd1;
            end
        end
    end

    assign cociente = coc_reg;
    assign resto    = resto_reg;

endmodule

src/z_pruebas_funcionamiento/tb_operacion.sv
`timescale 1ns/1ps

module tb_operacion;

    // Señales del DUT
    logic        clk;
    logic        rst_n;      // reset global activo en bajo
    logic        start;      // pulso para iniciar la división
    logic [7:0]  a_bcd;      // {decenas, unidades}
    logic [7:0]  b_bcd;      // {decenas, unidades}
    logic [3:0]  cociente;   // salida del DUT
    logic [3:0]  resto;      // salida del DUT

    // Instancia del módulo bajo prueba
    operacion dut (
        .clk      (clk),
        .rst_n    (rst_n),
        .start    (start),
        .a_bcd    (a_bcd),
        .b_bcd    (b_bcd),
        .cociente (cociente),
        .resto    (resto)
    );

    //==================================================
    // Generación de reloj
    //==================================================
    initial clk = 0;
    always #10 clk = ~clk;   // periodo = 20 ns (50 MHz en simulación)

    //==================================================
    // Tarea para correr un caso de prueba
    // a_dec, a_uni, b_dec, b_uni son nibbles BCD
    //==================================================
    task automatic run_case(
        input string   name,
        input logic[3:0] a_dec, a_uni,
        input logic[3:0] b_dec, b_uni
    );
        logic [7:0]  local_a_bcd, local_b_bcd;
        logic [3:0]  A_bin, B_bin;
        logic [3:0]  exp_q, exp_r;
    begin
        // Armar valores BCD
        local_a_bcd = {a_dec, a_uni};
        local_b_bcd = {b_dec, b_uni};

        // Aplicar a entradas
        a_bcd = local_a_bcd;
        b_bcd = local_b_bcd;

        // Calcular A_bin y B_bin EXACTAMENTE igual que en el DUT
        A_bin = ((a_dec == 4'b0001) ? 4'b1010 : 4'b0000) +
                ((a_uni != 4'b1111) ? a_uni    : 4'b0000);

        B_bin = ((b_dec == 4'b0001) ? 4'b1010 : 4'b0000) +
                ((b_uni != 4'b1111) ? b_uni    : 4'b0000);

        if (B_bin == 0) begin
            // si divisor = 0, el comportamiento del DUT no está definido,
            // así que aquí evitamos esos casos
            $display("[%0t] WARNING %s: B_bin=0, se omite este caso", $time, name);
            disable run_case;
        end

        // Resultado esperado
        exp_q = A_bin / B_bin;
        exp_r = A_bin % B_bin;

        // Generar pulso de start (1 ciclo de reloj)
        start = 1'b1;
        @(posedge clk);
        start = 1'b0;

        // El algoritmo necesita 4 ciclos (un bit por ciclo).
        // Sumamos margen y esperamos 6 flancos
        repeat (6) @(posedge clk);

        // Comprobaciones
        if (cociente !== exp_q || resto !== exp_r) begin
            $display("[%0t] TEST %s: FAIL", $time, name);
            $display("       A_bcd=%h (A_bin=%0d), B_bcd=%h (B_bin=%0d)",
                     local_a_bcd, A_bin, local_b_bcd, B_bin);
            $display("       Esperado: Q=%0d, R=%0d", exp_q, exp_r);
            $display("       Obtenido: Q=%0d, R=%0d", cociente, resto);
            $fatal(1);
        end else begin
            $display("[%0t] TEST %s: OK  A_bin=%0d / B_bin=%0d => Q=%0d, R=%0d",
                     $time, name, A_bin, B_bin, cociente, resto);
        end
    end
    endtask

    //==================================================
    // Estímulos
    //==================================================
    initial begin
        // Para ver señales en GTKWave o similar
        $dumpfile("tb_operacion.vcd");
        $dumpvars(0, tb_operacion);

        // Valores iniciales
        rst_n = 1'b0;
        start = 1'b0;
        a_bcd = 8'h00;
        b_bcd = 8'h00;

        // Sacamos del reset
        @(posedge clk);
        rst_n = 1'b1;
        @(posedge clk);

        // ------------------------
        // Casos de prueba
        // ------------------------
        // Recuerda: A_bin = (decena==1 ? 10 : 0) + unidades

        // Caso 1:  A = 0x04 => A_bin = 4
        //          B = 0x02 => B_bin = 2
        //          4/2 = 2, r=0
        run_case("A=04, B=02", 4'd0, 4'd4, 4'd0, 4'd2);

        // Caso 2:  A = 0x09 => 9, B = 0x03 => 3 => 9/3 = 3, r=0
        run_case("A=09, B=03", 4'd0, 4'd9, 4'd0, 4'd3);

        // Caso 3:  A = 0x12 => A_bin = 10+2 = 12
        //          B = 0x04 => B_bin = 4 => 12/4 = 3, r=0
        run_case("A=12, B=04", 4'd1, 4'd2, 4'd0, 4'd4);

        // Caso 4:  A = 0x15 => 10+5=15
        //          B = 0x06 => 6 => 15/6 = 2, r=3
        run_case("A=15, B=06", 4'd1, 4'd5, 4'd0, 4'd6);

        $display("[%0t] Todos los tests PASARON", $time);
        $finish;
    end

endmodule

src/build/tb_operacion.vcd
$date
	Fri Nov 28 23:07:54 2025
$end
$version
	Icarus Verilog
$end
$timescale
	1ps
$end
$scope module tb_operacion $end
$var wire 4 ! resto [3:0] $end
$var wire 4 " cociente [3:0] $end
$var reg 8 # a_bcd [7:0] $end
$var reg 8 $ b_bcd [7:0] $end
$var reg 1 % clk $end
$var reg 1 & rst_n $end
$var reg 1 ' start $end
$scope module dut $end
$var wire 8 ( a_bcd [7:0] $end
$var wire 8 ) b_bcd [7:0] $end
$var wire 1 % clk $end
$var wire 4 * cociente [3:0] $end
$var wire 4 + resto [3:0] $end
$var wire 1 & rst_n $end
$var wire 1 ' start $end
$var reg 4 , A_bin [3:0] $end
$var reg 4 - B_bin [3:0] $end
$var reg 5 . D [4:0] $end
$var reg 4 / R_shift [3:0] $end
$var reg 4 0 a_dec [3:0] $end
$var reg 4 1 a_uni [3:0] $end
$var reg 4 2 b_dec [3:0] $end
$var reg 4 3 b_uni [3:0] $end
$var reg 4 4 coc_reg [3:0] $end
$var reg 2 5 idx [1:0] $end
$var reg 4 6 resto_reg [3:0] $end
$var reg 1 7 running $end
$upscope $end
$scope task run_case $end
$upscope $end
$upscope $end
$enddefinitions $end
$comment Show the parameter values. $end
$dumpall
$end
#0
$dumpvars
07
b0 6
b0 5
b0 4
b0 3
b0 2
b0 1
b0 0
b0 /
b0 .
b0 -
b0 ,
b0 +
b0 *
b0 )
b0 (
0'
0&
0%
b0 $
b0 #
b0 "
b0 !
$end
#10000
1&
1%
#20000
0%
#30000
17
b11 5
b11110 .
b10 -
b100 ,
b10 3
b100 1
1'
b10 $
b10 )
b100 #
b100 (
1%
#40000
0%
#50000
b11111 .
b1 /
b10 5
0'
1%
#60000
0%
#70000
b0 .
b10 /
b1 5
b1 !
b1 +
b1 6
1%
#80000
0%
#90000
b11110 .
b0 /
b0 5
b0 !
b0 +
b0 6
b10 "
b10 *
b10 4
1%
#100000
0%
#110000
07
1%
#120000
0%
#130000
1%
#140000
0%
#150000
1%
#160000
0%
#170000
17
b11 5
b0 "
b0 *
b0 4
b1 /
b11 -
b1001 ,
b11 3
b1001 1
1'
b11 $
b11 )
b1001 #
b1001 (
1%
#180000
0%
#190000
b11111 .
b10 /
b10 5
b1 !
b1 +
b1 6
0'
1%
#200000
0%
#210000
b1 .
b100 /
b1 5
b10 !
b10 +
b10 6
1%
#220000
0%
#230000
b0 .
b11 /
b0 5
b1 !
b1 +
b1 6
b10 "
b10 *
b10 4
1%
#240000
0%
#250000
b11110 .
b1 /
07
b0 !
b0 +
b0 6
b11 "
b11 *
b11 4
1%
#260000
0%
#270000
1%
#280000
0%
#290000
1%
#300000
0%
#310000
17
b11 5
b0 "
b0 *
b0 4
b11101 .
b1 /
b100 -
b1100 ,
b100 3
b10 1
b1010 0
1'
b100 $
b100 )
b10010 #
b10010 (
1%
#320000
0%
#330000
b11111 .
b11 /
b10 5
b1 !
b1 +
b1 6
0'
1%
#340000
0%
#350000
b10 .
b110 /
b1 5
b11 !
b11 +
b11 6
1%
#360000
0%
#370000
b0 .
b100 /
b0 5
b10 !
b10 +
b10 6
b10 "
b10 *
b10 4
1%
#380000
0%
#390000
b11100 .
b0 /
07
b0 !
b0 +
b0 6
b11 "
b11 *
b11 4
1%
#400000
0%
#410000
1%
#420000
0%
#430000
1%
#440000
0%
#450000
17
b11 5
b0 "
b0 *
b0 4
b11011 .
b1 /
b110 -
b1111 ,
b110 3
b101 1
1'
b110 $
b110 )
b10101 #
b10101 (
1%
#460000
0%
#470000
b11101 .
b11 /
b10 5
b1 !
b1 +
b1 6
0'
1%
#480000
0%
#490000
b1 .
b111 /
b1 5
b11 !
b11 +
b11 6
1%
#500000
0%
#510000
b11101 .
b11 /
b0 5
b1 !
b1 +
b1 6
b10 "
b10 *
b10 4
1%
#520000
0%
#530000
b1 .
b111 /
07
b11 !
b11 +
b11 6
1%
