src/design/teclado.sv
module teclado #(
    parameter int SCAN_DIV = 13_500  // ~0.5 ms por columna @27MHz
)(
    // Entradas
    input  logic clk,
    input  logic [3:0] filas,
    // Salidas
    output logic [3:0] columnas,
    output logic [3:0] boton
);
    // Variables
    logic [1:0] contador = 0;
    logic [$clog2(SCAN_DIV)-1:0] scan_col = 0;
    //initial boton = 4'b1111;
    
    always_ff @(posedge clk) begin
        // divisor para cambio de columna
        if (scan_col == SCAN_DIV-1) begin
            scan_col <= 0;
            contador <= (contador == 3) ? 0: contador + 1;
        end else begin
            scan_col <= scan_col + 1;
        end        
        
        // Asigno valores de columnas One - Hot
        case(contador)
            0: columnas <= 4'b0111;
            1: columnas <= 4'b1011;
            2: columnas <= 4'b1101;
            3: columnas <= 4'b1110;
        endcase
        case(columnas)
            4'b0111:begin
                if(filas == 4'b0111) boton <= 4'b0001; //1
                if(filas == 4'b1011) boton <= 4'b0100; //4
                if(filas == 4'b1101) boton <= 4'b0111; //7
                if(filas == 4'b1110) boton <= 4'b0000; //*
            end

            4'b1011:begin
                if(filas == 4'b0111) boton <= 4'b0010; //2
                if(filas == 4'b1011) boton <= 4'b0101; //5
                if(filas == 4'b1101) boton <= 4'b1000; //8
                if(filas == 4'b1110) boton <= 4'b0000; //0
            end

            4'b1101:begin
                if(filas == 4'b0111) boton <= 4'b0011; //3
                if(filas == 4'b1011) boton <= 4'b0110; //6
                if(filas == 4'b1101) boton <= 4'b1001; //9
                if(filas == 4'b1110) boton <= 4'b1110; //#
            end

            4'b1110:begin
                if(filas == 4'b0111) boton <= 4'b1010; //A
                if(filas == 4'b1011) boton <= 4'b1011; //B
                if(filas == 4'b1101) boton <= 4'b1100; //C
                if(filas == 4'b1110) boton <= 4'b1101; //D
            end
            default: boton <= 4'b1111;
        endcase
    end
endmodule

src/sim/tb_teclado.sv
`timescale 1ns/1ps

module tb_teclado;

    // Señales del testbench
    logic       clk;
    logic [3:0] filas;
    logic [3:0] columnas;
    logic [3:0] boton;

    // Instancia del DUT
    teclado dut (
        .clk     (clk),
        .filas   (filas),
        .columnas(columnas),
        .boton   (boton)
    );

    // Reloj: 10 ns de periodo
    initial clk = 0;
    always #5 clk = ~clk;

    // Tarea: presionar una tecla durante varios ciclos y comprobar el valor
    task automatic presionar_tecla(
        input logic [3:0] fila_activar,   // patrón de filas (una en 0)
        input logic [3:0] valor_esperado, // valor esperado en 'boton'
        input string      nombre          // nombre de la tecla para mensajes
    );
        int i;
        bit ok;

        begin
            ok = 0;

            // Simular que la tecla está presionada
            filas = fila_activar;

            // Dejamos pasar varios ciclos para que el escáner recorra columnas
            for (i = 0; i < 16; i++) begin
                @(posedge clk);
                #1; // pequeña espera para estabilizar

                if (boton === valor_esperado) begin
                    ok = 1;
                    $display("OK tecla %s: boton=%b (columnas=%b, filas=%b, t=%0t)",
                             nombre, boton, columnas, filas, $time);
                    break;
                end
            end

            if (!ok) begin
                $error("ERROR tecla %s: esperado=%b, nunca se obtuvo ese valor. Último boton=%b (columnas=%b, filas=%b, t=%0t)",
                       nombre, valor_esperado, boton, columnas, filas, $time);
            end

            // Soltar la tecla
            filas = 4'b1111;
            // Esperar unos ciclos sin tecla
            repeat (4) @(posedge clk);
        end
    endtask

    // Estímulos
    initial begin
        // Inicialización
        filas = 4'b1111;     // ninguna tecla presionada

        // Para evitar 'X' en simulación, inicializamos contador (solo simulación)
        dut.contador = 0;

        // Esperar a que el DUT empiece a escanear
        repeat (8) @(posedge clk);

        // *** FILA 0: filas = 0111 -> 1,2,3,A ***
        presionar_tecla(4'b0111, 4'b0001, "1"); // col=0111
        presionar_tecla(4'b0111, 4'b0010, "2"); // col=1011
        presionar_tecla(4'b0111, 4'b0011, "3"); // col=1101
        presionar_tecla(4'b0111, 4'b0110, "A"); // col=1110 (según tu código, A=0110)

        // *** FILA 1: filas = 1011 -> 4,5,6,B ***
        presionar_tecla(4'b1011, 4'b0100, "4"); // col=0111
        presionar_tecla(4'b1011, 4'b0101, "5"); // col=1011
        presionar_tecla(4'b1011, 4'b0110, "6"); // col=1101
        presionar_tecla(4'b1011, 4'b1011, "B"); // col=1110

        // *** FILA 2: filas = 1101 -> 7,8,9,C ***
        presionar_tecla(4'b1101, 4'b0111, "7"); // col=0111
        presionar_tecla(4'b1101, 4'b1000, "8"); // col=1011
        presionar_tecla(4'b1101, 4'b1001, "9"); // col=1101
        presionar_tecla(4'b1101, 4'b1100, "C"); // col=1110

        // *** FILA 3: filas = 1110 -> *,0,#,D ***
        // Ojo: en tu diseño, *, 0 y # comparten el mismo valor 0000
        presionar_tecla(4'b1110, 4'b0000, "*"); // col=0111
        presionar_tecla(4'b1110, 4'b0000, "0"); // col=1011
        presionar_tecla(4'b1110, 4'b0000, "#"); // col=1101
        presionar_tecla(4'b1110, 4'b1101, "D"); // col=1110

        $display("Fin de la simulación: todas las teclas probadas.");
        $finish;
    end

    // Volcado de señales
    initial begin
        $dumpfile("tb_teclado.vcd");
        $dumpvars(0, tb_teclado);
    end

endmodule

src/build/tb_teclado.vcd
$date
	Sun Nov 16 18:37:32 2025
$end
$version
	Icarus Verilog
$end
$timescale
	1ps
$end
$scope module tb_teclado $end
$var wire 4 ! columnas [3:0] $end
$var wire 4 " boton [3:0] $end
$var reg 1 # clk $end
$var reg 4 $ filas [3:0] $end
$scope module dut $end
$var wire 1 # clk $end
$var wire 4 % filas [3:0] $end
$var reg 4 & boton [3:0] $end
$var reg 4 ' columnas [3:0] $end
$var reg 2 ( contador [1:0] $end
$upscope $end
$scope task presionar_tecla $end
$upscope $end
$upscope $end
$enddefinitions $end
$comment Show the parameter values. $end
$dumpall
$end
#0
$dumpvars
b0 (
bx '
b1111 &
b1111 %
b1111 $
0#
b1111 "
bx !
$end
#5000
b111 !
b111 '
b1 (
1#
#10000
0#
#15000
b1011 !
b1011 '
b10 (
1#
#20000
0#
#25000
b1101 !
b1101 '
b11 (
1#
#30000
0#
#35000
b1110 !
b1110 '
b0 (
1#
#40000
0#
#45000
b111 !
b111 '
b1 (
1#
#50000
0#
#55000
b1011 !
b1011 '
b10 (
1#
#60000
0#
#65000
b1101 !
b1101 '
b11 (
1#
#70000
0#
#75000
b1110 !
b1110 '
b0 (
b111 $
b111 %
1#
#80000
0#
#85000
b110 "
b110 &
b111 !
b111 '
b1 (
1#
#90000
0#
#95000
b1 "
b1 &
b1011 !
b1011 '
b10 (
1#
#96000
b1111 $
b1111 %
#100000
0#
#105000
b1101 !
b1101 '
b11 (
1#
#110000
0#
#115000
b1110 !
b1110 '
b0 (
1#
#120000
0#
#125000
b111 !
b111 '
b1 (
1#
#130000
0#
#135000
b1011 !
b1011 '
b10 (
b111 $
b111 %
1#
#140000
0#
#145000
b10 "
b10 &
b1101 !
b1101 '
b11 (
1#
#146000
b1111 $
b1111 %
#150000
0#
#155000
b1110 !
b1110 '
b0 (
1#
#160000
0#
#165000
b111 !
b111 '
b1 (
1#
#170000
0#
#175000
b1011 !
b1011 '
b10 (
1#
#180000
0#
#185000
b1101 !
b1101 '
b11 (
b111 $
b111 %
1#
#190000
0#
#195000
b11 "
b11 &
b1110 !
b1110 '
b0 (
1#
#196000
b1111 $
b1111 %
#200000
0#
#205000
b111 !
b111 '
b1 (
1#
#210000
0#
#215000
b1011 !
b1011 '
b10 (
1#
#220000
0#
#225000
b1101 !
b1101 '
b11 (
1#
#230000
0#
#235000
b1110 !
b1110 '
b0 (
b111 $
b111 %
1#
#240000
0#
#245000
b110 "
b110 &
b111 !
b111 '
b1 (
1#
#246000
b1111 $
b1111 %
#250000
0#
#255000
b1011 !
b1011 '
b10 (
1#
#260000
0#
#265000
b1101 !
b1101 '
b11 (
1#
#270000
0#
#275000
b1110 !
b1110 '
b0 (
1#
#280000
0#
#285000
b111 !
b111 '
b1 (
b1011 $
b1011 %
1#
#290000
0#
#295000
b100 "
b100 &
b1011 !
b1011 '
b10 (
1#
#296000
b1111 $
b1111 %
#300000
0#
#305000
b1101 !
b1101 '
b11 (
1#
#310000
0#
#315000
b1110 !
b1110 '
b0 (
1#
#320000
0#
#325000
b111 !
b111 '
b1 (
1#
#330000
0#
#335000
b1011 !
b1011 '
b10 (
b1011 $
b1011 %
1#
#340000
0#
#345000
b101 "
b101 &
b1101 !
b1101 '
b11 (
1#
#346000
b1111 $
b1111 %
#350000
0#
#355000
b1110 !
b1110 '
b0 (
1#
#360000
0#
#365000
b111 !
b111 '
b1 (
1#
#370000
0#
#375000
b1011 !
b1011 '
b10 (
1#
#380000
0#
#385000
b1101 !
b1101 '
b11 (
b1011 $
b1011 %
1#
#390000
0#
#395000
b110 "
b110 &
b1110 !
b1110 '
b0 (
1#
#396000
b1111 $
b1111 %
#400000
0#
#405000
b111 !
b111 '
b1 (
1#
#410000
0#
#415000
b1011 !
b1011 '
b10 (
1#
#420000
0#
#425000
b1101 !
b1101 '
b11 (
1#
#430000
0#
#435000
b1110 !
b1110 '
b0 (
b1011 $
b1011 %
1#
#440000
0#
#445000
b1011 "
b1011 &
b111 !
b111 '
b1 (
1#
#446000
b1111 $
b1111 %
#450000
0#
#455000
b1011 !
b1011 '
b10 (
1#
#460000
0#
#465000
b1101 !
b1101 '
b11 (
1#
#470000
0#
#475000
b1110 !
b1110 '
b0 (
1#
#480000
0#
#485000
b111 !
b111 '
b1 (
b1101 $
b1101 %
1#
#490000
0#
#495000
b111 "
b111 &
b1011 !
b1011 '
b10 (
1#
#496000
b1111 $
b1111 %
#500000
0#
#505000
b1101 !
b1101 '
b11 (
1#
#510000
0#
#515000
b1110 !
b1110 '
b0 (
1#
#520000
0#
#525000
b111 !
b111 '
b1 (
1#
#530000
0#
#535000
b1011 !
b1011 '
b10 (
b1101 $
b1101 %
1#
#540000
0#
#545000
b1000 "
b1000 &
b1101 !
b1101 '
b11 (
1#
#546000
b1111 $
b1111 %
#550000
0#
#555000
b1110 !
b1110 '
b0 (
1#
#560000
0#
#565000
b111 !
b111 '
b1 (
1#
#570000
0#
#575000
b1011 !
b1011 '
b10 (
1#
#580000
0#
#585000
b1101 !
b1101 '
b11 (
b1101 $
b1101 %
1#
#590000
0#
#595000
b1001 "
b1001 &
b1110 !
b1110 '
b0 (
1#
#596000
b1111 $
b1111 %
#600000
0#
#605000
b111 !
b111 '
b1 (
1#
#610000
0#
#615000
b1011 !
b1011 '
b10 (
1#
#620000
0#
#625000
b1101 !
b1101 '
b11 (
1#
#630000
0#
#635000
b1110 !
b1110 '
b0 (
b1101 $
b1101 %
1#
#640000
0#
#645000
b1100 "
b1100 &
b111 !
b111 '
b1 (
1#
#646000
b1111 $
b1111 %
#650000
0#
#655000
b1011 !
b1011 '
b10 (
1#
#660000
0#
#665000
b1101 !
b1101 '
b11 (
1#
#670000
0#
#675000
b1110 !
b1110 '
b0 (
1#
#680000
0#
#685000
b111 !
b111 '
b1 (
b1110 $
b1110 %
1#
#690000
0#
#695000
b0 "
b0 &
b1011 !
b1011 '
b10 (
1#
#696000
b1111 $
b1111 %
#700000
0#
#705000
b1101 !
b1101 '
b11 (
1#
#710000
0#
#715000
b1110 !
b1110 '
b0 (
1#
#720000
0#
#725000
b111 !
b111 '
b1 (
1#
#730000
0#
#735000
b1011 !
b1011 '
b10 (
b1110 $
b1110 %
1#
#740000
0#
#745000
b1101 !
b1101 '
b11 (
1#
#746000
b1111 $
b1111 %
#750000
0#
#755000
b1110 !
b1110 '
b0 (
1#
#760000
0#
#765000
b111 !
b111 '
b1 (
1#
#770000
0#
#775000
b1011 !
b1011 '
b10 (
1#
#780000
0#
#785000
b1101 !
b1101 '
b11 (
b1110 $
b1110 %
1#
#790000
0#
#795000
b1110 !
b1110 '
b0 (
1#
#796000
b1111 $
b1111 %
#800000
0#
#805000
b111 !
b111 '
b1 (
1#
#810000
0#
#815000
b1011 !
b1011 '
b10 (
1#
#820000
0#
#825000
b1101 !
b1101 '
b11 (
1#
#830000
0#
#835000
b1110 !
b1110 '
b0 (
b1110 $
b1110 %
1#
#840000
0#
#845000
b1101 "
b1101 &
b111 !
b111 '
b1 (
1#
#846000
b1111 $
b1111 %
#850000
0#
#855000
b1011 !
b1011 '
b10 (
1#
#860000
0#
#865000
b1101 !
b1101 '
b11 (
1#
#870000
0#
#875000
b1110 !
b1110 '
b0 (
1#
#880000
0#
#885000
b111 !
b111 '
b1 (
1#
